bdgd_tools/__init__.py
bdgd_tools/core/Core.py
bdgd_tools/core/Utils.py
bdgd_tools/core/__init__.py
bdgd_tools/gui/GUI.py
bdgd_tools/gui/__init__.py
bdgd_tools/model/BusCoords.py
bdgd_tools/model/Capacitor.py
bdgd_tools/model/Case.py
bdgd_tools/model/Circuit.py
bdgd_tools/model/Converter.py
bdgd_tools/model/Count_days.py
bdgd_tools/model/LineCode.py
bdgd_tools/model/Loadshape.py
bdgd_tools/model/__init__.py
bdgd_tools/sample/Sample.py
bdgd_tools/sample/__init__.py
bdgd_tools-1.0.4.dist-info/AUTHORS.rst
bdgd_tools-1.0.4.dist-info/LICENSE
bdgd_tools-1.0.4.dist-info/METADATA
bdgd_tools-1.0.4.dist-info/WHEEL
bdgd_tools-1.0.4.dist-info/top_level.txt
bdgd_tools-1.0.4.dist-info/RECORD
