Metadata-Version: 2.1
Name: bdgd-tools
Version: 1.0.4
Summary: Short description
Home-page: https://github.com/eniocc/bdgd_tools
Author: Ênio Rodrigues
Author-email: eniocc@gmail.com
License: MIT license
Keywords: bdgd_tools
Classifier: Development Status :: 2 - Pre-Alpha
Classifier: Intended Audience :: Developers
Classifier: License :: OSI Approved :: MIT License
Classifier: Natural Language :: English
Classifier: Programming Language :: Python :: 3
Classifier: Programming Language :: Python :: 3.9
Requires-Python: >=3.9
License-File: LICENSE
License-File: AUTHORS.rst
